GalDynPsrSuper/ExGal_fdot_MC.py
GalDynPsrSuper/ExGal_fdot_MW.py
GalDynPsrSuper/ExGal_pdot_MC.py
GalDynPsrSuper/ExGal_pdot_MW.py
GalDynPsrSuper/ExShk_fdot.py
GalDynPsrSuper/ExShk_pdot.py
GalDynPsrSuper/Ex_fdotdot_MC.py
GalDynPsrSuper/Ex_fdotdot_MW.py
GalDynPsrSuper/Ex_pdotdot_MC.py
GalDynPsrSuper/Ex_pdotdot_MW.py
GalDynPsrSuper/README.txt
GalDynPsrSuper/__init__.py
GalDynPsrSuper/parameters.in
GalDynPsrSuper/read_parameters.py
GalDynPsrSuper-0.0.1.dist-info/LICENSE
GalDynPsrSuper-0.0.1.dist-info/METADATA
GalDynPsrSuper-0.0.1.dist-info/WHEEL
GalDynPsrSuper-0.0.1.dist-info/top_level.txt
GalDynPsrSuper-0.0.1.dist-info/RECORD
