Metadata-Version: 2.1
Name: GalDynPsrSuper
Version: 0.0.1
Summary: A package for estimating contribution of dynamical terms in the first and second derivatives of frequencies as well as periods (both spin and orbital) of pulsars.
Home-page: https://github.com/pathakdhruv/GalDynPsrSuper
Author: Dhruv Pathak
Author-email: pathakdhruv9786@gmail.com
License: New BSD
Classifier: Programming Language :: Python :: 3
Classifier: License :: OSI Approved :: BSD License
Classifier: Operating System :: OS Independent
License-File: LICENSE
